HousePricePrediction/ingest_data.py
HousePricePrediction/score.py
HousePricePrediction/train.py
housing_library_5506-0.1.dist-info/METADATA
housing_library_5506-0.1.dist-info/WHEEL
housing_library_5506-0.1.dist-info/entry_points.txt
housing_library_5506-0.1.dist-info/top_level.txt
housing_library_5506-0.1.dist-info/RECORD
