Metadata-Version: 2.1
Name: housing-library-5506
Version: 0.1
Summary: Sample code for coding practice
Author-email: vemani-vutlapalli <vemani.vutlapall@tigeranalytics.com>
Project-URL: Homepage, https://github.com/vemani5506/mle-training.git
Keywords: housing,data training
Classifier: Programming Language :: Python :: 3
Requires-Python: >=3.11
Requires-Dist: numpy
Requires-Dist: pandas
Requires-Dist: scikit-learn
